domino/__init__.py
domino/_version.py
domino/authentication.py
domino/constants.py
domino/data_sources.py
domino/domino.py
domino/exceptions.py
domino/helpers.py
domino/http_request_manager.py
domino/routes.py
domino/training_sets.py
domino/airflow/__init__.py
domino/airflow/_operator.py
fastdomino-1.0.7.dist-info/LICENSE.txt
fastdomino-1.0.7.dist-info/METADATA
fastdomino-1.0.7.dist-info/WHEEL
fastdomino-1.0.7.dist-info/top_level.txt
fastdomino-1.0.7.dist-info/RECORD
