Metadata-Version: 2.1
Name: fastdomino
Version: 1.0.7
Summary: Python bindings for the Domino API Fork by fast.co
Home-page: https://github.com/fast-af/python-domino
Author: Hao Xu
Author-email: hao.xu@fast.co
License: Apache Software License (Apache 2.0)
Download-URL: https://github.com/fast-af/python-domino/archive/1.0.7.zip
Keywords: Domino Data Lab,API,FAST
Platform: UNKNOWN
License-File: LICENSE.txt
Requires-Dist: requests (>=2.4.2)
Requires-Dist: bs4 (==0.*,>=0.0.1)
Requires-Dist: polling2
Provides-Extra: airflow
Requires-Dist: apache-airflow (==1.*,>=1.10) ; extra == 'airflow'
Provides-Extra: data
Requires-Dist: dominodatalab-data (>=0.1.0) ; extra == 'data'
